LICENSE
MANIFEST.in
README.md
setup.py
honey/__init__.py
honey/base/__init__.py
honey/base/cmn/__env.py
honey/base/cmn/__init__.py
honey/base/gui/__init__.py
honey/base/gui/__media.py
honey/base/gui/__plot.py
honey/base/io/__cmd.py
honey/base/io/__file.py
honey/base/io/__init__.py
honey/base/log/__init__.py
honey/base/log/__log.py
honey/base/math/__init__.py
honey/base/net/__http.py
honey/base/net/__init__.py
honey/base/opencv/__init__.py
honey/base/plot/__init__.py
honey/base/secure/__bcode.py
honey/base/secure/__hash.py
honey/base/secure/__init__.py
honey/base/thread/__init__.py
honey/base/thread/__thread.py
honey/base/thread/__timer.py
honey/base/util/__arrays.py
honey/base/util/__colls.py
honey/base/util/__csv.py
honey/base/util/__date.py
honey/base/util/__email.py
honey/base/util/__init__.py
honey/base/util/__string.py
honey/base/util/__zk.py
honey_base.egg-info/PKG-INFO
honey_base.egg-info/SOURCES.txt
honey_base.egg-info/dependency_links.txt
honey_base.egg-info/not-zip-safe
honey_base.egg-info/requires.txt
honey_base.egg-info/top_level.txt