Metadata-Version: 1.1
Name: honey-base
Version: 0.0.3
Summary: it's a useful common toolkit for pythoner
Home-page: UNKNOWN
Author: geekbruce
Author-email: bruce.shaoheng@mgail.com
License: UNKNOWN
Platform: UNKNOWN
Classifier: Development Status :: 3 - Alpha
Classifier: Topic :: Utilities
Classifier: License :: OSI Approved :: GNU General Public License (GPL)
Classifier: Programming Language :: Python :: 3
